pytorch_autotune/__init__.py
pytorch_autotune/autotune.py
pytorch_autotune-1.0.2.dist-info/licenses/LICENSE
pytorch_autotune-1.0.2.dist-info/METADATA
pytorch_autotune-1.0.2.dist-info/WHEEL
pytorch_autotune-1.0.2.dist-info/top_level.txt
pytorch_autotune-1.0.2.dist-info/RECORD
