Metadata-Version: 2.4
Name: pytorch-autotune
Version: 1.0.2
Summary: Automatic 4x training speedup for PyTorch models
Home-page: https://github.com/JonSnow1807/pytorch-autotune
Author: Chinmay Shrivastava
Author-email: cshrivastava2000@gmail.com
License: MIT
Project-URL: Bug Reports, https://github.com/JonSnow1807/pytorch-autotune/issues
Project-URL: Source, https://github.com/JonSnow1807/pytorch-autotune
Project-URL: Documentation, https://github.com/JonSnow1807/pytorch-autotune#readme
Project-URL: License, https://github.com/JonSnow1807/pytorch-autotune/blob/main/LICENSE
Keywords: pytorch optimization speedup training acceleration autotune
Classifier: Development Status :: 4 - Beta
Classifier: Intended Audience :: Developers
Classifier: Topic :: Scientific/Engineering :: Artificial Intelligence
Classifier: License :: OSI Approved :: MIT License
Classifier: Programming Language :: Python :: 3
Classifier: Programming Language :: Python :: 3.7
Classifier: Programming Language :: Python :: 3.8
Classifier: Programming Language :: Python :: 3.9
Classifier: Programming Language :: Python :: 3.10
Classifier: Programming Language :: Python :: 3.11
Requires-Python: >=3.7
License-File: LICENSE
Requires-Dist: torch>=2.0.0
Requires-Dist: numpy>=1.19.0
Dynamic: author
Dynamic: author-email
Dynamic: classifier
Dynamic: description
Dynamic: description-content-type
Dynamic: home-page
Dynamic: keywords
Dynamic: license
Dynamic: license-file
Dynamic: project-url
Dynamic: requires-dist
Dynamic: requires-python
Dynamic: summary
